{
    "testEngine": {
        "name": "axe-core",
        "version": "4.4.3"
    },
    "testRunner": {
        "name": "axe"
    },
    "timestamp": "2024-09-26T06:28:23.033Z",
    "url": "https://insightchemicals.3eiq.com/Register.aspx",
    "toolOptions": {
        "resultTypes": [
            "violations"
        ],
        "reporter": "v1"
    },
    "passes": [
        {
            "id": "aria-allowed-role",
            "impact": null,
            "tags": [
                "cat.aria",
                "best-practice"
            ],
            "description": "Ensures role attribute has an appropriate value for the element",
            "help": "ARIA role should be appropriate for the element",
            "helpUrl": "https://dequeuniversity.com/rules/axe/4.4/aria-allowed-role?application=axeAPI",
            "nodes": [
                {
                    "any": [
                        {
                            "id": "aria-allowed-role",
                            "data": null,
                            "relatedNodes": [],
                            "impact": "minor",
                            "message": "ARIA role is allowed for given element"
                        }
                    ],
                    "all": [],
                    "none": [],
                    "impact": null,
                    "html": "<ul class=\"level1 static\" tabindex=\"0\" role=\"menubar\" style=\"position: relative; width: auto; float: left;\">",
                    "target": [
                        "ul"
                    ]
                }
            ]
        },
        {
            "id": "aria-hidden-body",
            "impact": null,
            "tags": [
                "cat.aria",
                "wcag2a",
                "wcag412"
            ],
            "description": "Ensures aria-hidden='true' is not present on the document body.",
            "help": "aria-hidden='true' must not be present on the document body",
            "helpUrl": "https://dequeuniversity.com/rules/axe/4.4/aria-hidden-body?application=axeAPI",
            "nodes": [
                {
                    "any": [
                        {
                            "id": "aria-hidden-body",
                            "data": null,
                            "relatedNodes": [],
                            "impact": "critical",
                            "message": "No aria-hidden attribute is present on document body"
                        }
                    ],
                    "all": [],
                    "none": [],
                    "impact": null,
                    "html": "<body style=\"margin-left: 0; margin-right: 0; margin-top: 0; margin-bottom: 0\" onload=\"javascript:GotoTopFrame();configureUI(false);\" class=\"OutsisdeBox\">",
                    "target": [
                        "body"
                    ]
                }
            ]
        },
        {
            "id": "aria-hidden-focus",
            "impact": null,
            "tags": [
                "cat.name-role-value",
                "wcag2a",
                "wcag412",
                "wcag131"
            ],
            "description": "Ensures aria-hidden elements are not focusable nor contain focusable elements",
            "help": "ARIA hidden element must not be focusable or contain focusable elements",
            "helpUrl": "https://dequeuniversity.com/rules/axe/4.4/aria-hidden-focus?application=axeAPI",
            "nodes": [
                {
                    "any": [],
                    "all": [
                        {
                            "id": "focusable-modal-open",
                            "data": null,
                            "relatedNodes": [],
                            "impact": "serious",
                            "message": "No focusable elements while a modal is open"
                        },
                        {
                            "id": "focusable-disabled",
                            "data": null,
                            "relatedNodes": [],
                            "impact": "serious",
                            "message": "No focusable elements contained within element"
                        },
                        {
                            "id": "focusable-not-tabbable",
                            "data": null,
                            "relatedNodes": [],
                            "impact": "serious",
                            "message": "No focusable elements contained within element"
                        }
                    ],
                    "none": [],
                    "impact": null,
                    "html": "<div aria-hidden=\"true\" style=\"background-color: rgb(255, 255, 255); border: 1px solid rgb(215, 215, 215); box-shadow: rgba(0, 0, 0, 0.1) 0px 0px 4px; border-radius: 4px; left: auto; top: -10000px; z-index: -2147483648; position: absolute; pointer-events: auto; transition: opacity 0.15s ease-out; opacity: 0; visibility: hidden;\">",
                    "target": [
                        "div[aria-hidden=\"true\"]"
                    ]
                }
            ]
        },
        {
            "id": "avoid-inline-spacing",
            "impact": "serious",
            "tags": [
                "cat.structure",
                "wcag21aa",
                "wcag1412"
            ],
            "description": "Ensure that text spacing set through style attributes can be adjusted with custom stylesheets",
            "help": "Inline text spacing must be adjustable with custom stylesheets",
            "helpUrl": "https://dequeuniversity.com/rules/axe/4.4/avoid-inline-spacing?application=axeAPI",
            "nodes": [
                {
                    "any": [],
                    "all": [
                        {
                            "id": "avoid-inline-spacing",
                            "data": null,
                            "relatedNodes": [],
                            "impact": "serious",
                            "message": "No inline styles with '!important' that affect text spacing has been specified"
                        }
                    ],
                    "none": [],
                    "impact": null,
                    "html": "<body style=\"margin-left: 0; margin-right: 0; margin-top: 0; margin-bottom: 0\" onload=\"javascript:GotoTopFrame();configureUI(false);\" class=\"OutsisdeBox\">",
                    "target": [
                        "body"
                    ]
                }
            ]
        },
        {
            "id": "bypass",
            "impact": null,
            "tags": [
                "cat.keyboard",
                "wcag2a",
                "wcag241",
                "section508",
                "section508.22.o"
            ],
            "description": "Ensures each page has at least one mechanism for a user to bypass navigation and jump straight to the content",
            "help": "Page must have means to bypass repeated blocks",
            "helpUrl": "https://dequeuniversity.com/rules/axe/4.4/bypass?application=axeAPI",
            "nodes": [
                {
                    "any": [
                        {
                            "id": "internal-link-present",
                            "data": null,
                            "relatedNodes": [],
                            "impact": "serious",
                            "message": "Valid skip link found"
                        }
                    ],
                    "all": [],
                    "none": [],
                    "impact": null,
                    "html": "<html lang=\"en-US\" xml:lang=\"\" xmlns=\"http://www.w3.org/1999/xhtml\">",
                    "target": [
                        "html"
                    ]
                }
            ]
        },
        {
            "id": "color-contrast",
            "impact": "serious",
            "tags": [
                "cat.color",
                "wcag2aa",
                "wcag143"
            ],
            "description": "Ensures the contrast between foreground and background colors meets WCAG 2 AA contrast ratio thresholds",
            "help": "Elements must have sufficient color contrast",
            "helpUrl": "https://dequeuniversity.com/rules/axe/4.4/color-contrast?application=axeAPI",
            "nodes": [
                {
                    "any": [
                        {
                            "id": "color-contrast",
                            "data": {
                                "fgColor": "#0d4c68",
                                "bgColor": "#ffffff",
                                "contrastRatio": 9.33,
                                "fontSize": "15.0pt (20px)",
                                "fontWeight": "normal",
                                "messageKey": null,
                                "expectedContrastRatio": "4.5:1",
                                "shadowColor": null
                            },
                            "relatedNodes": [],
                            "impact": "serious",
                            "message": "Element has sufficient color contrast of 9.33"
                        }
                    ],
                    "all": [],
                    "none": [],
                    "impact": null,
                    "html": "<span class=\"Head\">\n                    Create a New Account\n                </span>",
                    "target": [
                        ".Head"
                    ]
                }
            ]
        },
        {
            "id": "document-title",
            "impact": null,
            "tags": [
                "cat.text-alternatives",
                "wcag2a",
                "wcag242",
                "ACT"
            ],
            "description": "Ensures each HTML document contains a non-empty <title> element",
            "help": "Documents must have <title> element to aid in navigation",
            "helpUrl": "https://dequeuniversity.com/rules/axe/4.4/document-title?application=axeAPI",
            "nodes": [
                {
                    "any": [
                        {
                            "id": "doc-has-title",
                            "data": null,
                            "relatedNodes": [],
                            "impact": "serious",
                            "message": "Document has a non-empty <title> element"
                        }
                    ],
                    "all": [],
                    "none": [],
                    "impact": null,
                    "html": "<html lang=\"en-US\" xml:lang=\"\" xmlns=\"http://www.w3.org/1999/xhtml\">",
                    "target": [
                        "html"
                    ]
                }
            ]
        },
        {
            "id": "duplicate-id-active",
            "impact": null,
            "tags": [
                "cat.parsing",
                "wcag2a",
                "wcag411"
            ],
            "description": "Ensures every id attribute value of active elements is unique",
            "help": "IDs of active elements must be unique",
            "helpUrl": "https://dequeuniversity.com/rules/axe/4.4/duplicate-id-active?application=axeAPI",
            "nodes": [
                {
                    "any": [
                        {
                            "id": "duplicate-id-active",
                            "data": "ctl00_ctl00_ContentPlaceHolderWhole_ContentPlaceHolderContent_FirstName",
                            "relatedNodes": [],
                            "impact": "serious",
                            "message": "Document has no active elements that share the same id attribute"
                        }
                    ],
                    "all": [],
                    "none": [],
                    "impact": null,
                    "html": "<input name=\"ctl00$ctl00$ContentPlaceHolderWhole$ContentPlaceHolderContent$FirstName\" type=\"text\" id=\"ctl00_ctl00_ContentPlaceHolderWhole_ContentPlaceHolderContent_FirstName\" size=\"25\">",
                    "target": [
                        "#ctl00_ctl00_ContentPlaceHolderWhole_ContentPlaceHolderContent_FirstName"
                    ]
                }
            ]
        },
        {
            "id": "duplicate-id",
            "impact": null,
            "tags": [
                "cat.parsing",
                "wcag2a",
                "wcag411"
            ],
            "description": "Ensures every id attribute value is unique",
            "help": "id attribute value must be unique",
            "helpUrl": "https://dequeuniversity.com/rules/axe/4.4/duplicate-id?application=axeAPI",
            "nodes": [
                {
                    "any": [
                        {
                            "id": "duplicate-id",
                            "data": "ctl00_ctl00_Head1",
                            "relatedNodes": [],
                            "impact": "minor",
                            "message": "Document has no static elements that share the same id attribute"
                        }
                    ],
                    "all": [],
                    "none": [],
                    "impact": null,
                    "html": "<head id=\"ctl00_ctl00_Head1\">",
                    "target": [
                        "#ctl00_ctl00_Head1"
                    ]
                }
            ]
        },
        {
            "id": "form-field-multiple-labels",
            "impact": null,
            "tags": [
                "cat.forms",
                "wcag2a",
                "wcag332"
            ],
            "description": "Ensures form field does not have multiple label elements",
            "help": "Form field must not have multiple label elements",
            "helpUrl": "https://dequeuniversity.com/rules/axe/4.4/form-field-multiple-labels?application=axeAPI",
            "nodes": [
                {
                    "any": [],
                    "all": [],
                    "none": [
                        {
                            "id": "multiple-label",
                            "data": null,
                            "relatedNodes": [],
                            "impact": "moderate",
                            "message": "Form field does not have multiple label elements"
                        }
                    ],
                    "impact": null,
                    "html": "<input name=\"ctl00$ctl00$ContentPlaceHolderWhole$ContentPlaceHolderContent$FirstName\" type=\"text\" id=\"ctl00_ctl00_ContentPlaceHolderWhole_ContentPlaceHolderContent_FirstName\" size=\"25\">",
                    "target": [
                        "#ctl00_ctl00_ContentPlaceHolderWhole_ContentPlaceHolderContent_FirstName"
                    ]
                }
            ]
        },
        {
            "id": "frame-title-unique",
            "impact": null,
            "tags": [
                "cat.text-alternatives",
                "best-practice"
            ],
            "description": "Ensures <iframe> and <frame> elements contain a unique title attribute",
            "help": "Frames should have a unique title attribute",
            "helpUrl": "https://dequeuniversity.com/rules/axe/4.4/frame-title-unique?application=axeAPI",
            "nodes": [
                {
                    "any": [],
                    "all": [],
                    "none": [
                        {
                            "id": "unique-frame-title",
                            "data": "widget containing checkbox for hcaptcha security challenge",
                            "relatedNodes": [],
                            "impact": "serious",
                            "message": "Element's title attribute is unique"
                        }
                    ],
                    "impact": null,
                    "html": "<iframe src=\"https://newassets.hcaptcha.com/captcha/v1/11178f2/static/hcaptcha.html#frame=checkbox&amp;id=07w8soj8gzpd&amp;host=insightchemicals.3eiq.com&amp;sentry=undefined&amp;reportapi=https%3A%2F%2Faccounts.hcaptcha.com&amp;recaptchacompat=true&amp;custom=false&amp;tplinks=on&amp;pstissuer=https%3A%2F%2Fpst-issuer.hcaptcha.com&amp;sitekey=b12cd44a-ddd4-4170-9761-927030c07eb5&amp;theme=light&amp;origin=https%3A%2F%2Finsightchemicals.3eiq.com\" tabindex=\"0\" frameborder=\"0\" scrolling=\"no\" allow=\"private-state-token-issuance 'src'; private-state-token-redemption 'src'\" title=\"Widget containing checkbox for hCaptcha security challenge\" data-hcaptcha-widget-id=\"07w8soj8gzpd\" data-hcaptcha-response=\"\" style=\"pointer-events: auto; background-color: rgba(255, 255, 255, 0); width: 303px; height: 78px; overflow: hidden;\">",
                    "target": [
                        "iframe[data-hcaptcha-widget-id=\"07w8soj8gzpd\"]"
                    ]
                }
            ]
        },
        {
            "id": "frame-title",
            "impact": null,
            "tags": [
                "cat.text-alternatives",
                "wcag2a",
                "wcag241",
                "wcag412",
                "section508",
                "section508.22.i"
            ],
            "description": "Ensures <iframe> and <frame> elements have an accessible name",
            "help": "Frames must have an accessible name",
            "helpUrl": "https://dequeuniversity.com/rules/axe/4.4/frame-title?application=axeAPI",
            "nodes": [
                {
                    "any": [
                        {
                            "id": "non-empty-title",
                            "data": null,
                            "relatedNodes": [],
                            "impact": "serious",
                            "message": "Element has a title attribute"
                        }
                    ],
                    "all": [],
                    "none": [],
                    "impact": null,
                    "html": "<iframe src=\"https://newassets.hcaptcha.com/captcha/v1/11178f2/static/hcaptcha.html#frame=checkbox&amp;id=07w8soj8gzpd&amp;host=insightchemicals.3eiq.com&amp;sentry=undefined&amp;reportapi=https%3A%2F%2Faccounts.hcaptcha.com&amp;recaptchacompat=true&amp;custom=false&amp;tplinks=on&amp;pstissuer=https%3A%2F%2Fpst-issuer.hcaptcha.com&amp;sitekey=b12cd44a-ddd4-4170-9761-927030c07eb5&amp;theme=light&amp;origin=https%3A%2F%2Finsightchemicals.3eiq.com\" tabindex=\"0\" frameborder=\"0\" scrolling=\"no\" allow=\"private-state-token-issuance 'src'; private-state-token-redemption 'src'\" title=\"Widget containing checkbox for hCaptcha security challenge\" data-hcaptcha-widget-id=\"07w8soj8gzpd\" data-hcaptcha-response=\"\" style=\"pointer-events: auto; background-color: rgba(255, 255, 255, 0); width: 303px; height: 78px; overflow: hidden;\">",
                    "target": [
                        "iframe[data-hcaptcha-widget-id=\"07w8soj8gzpd\"]"
                    ]
                }
            ]
        },
        {
            "id": "html-has-lang",
            "impact": null,
            "tags": [
                "cat.language",
                "wcag2a",
                "wcag311",
                "ACT"
            ],
            "description": "Ensures every HTML document has a lang attribute",
            "help": "<html> element must have a lang attribute",
            "helpUrl": "https://dequeuniversity.com/rules/axe/4.4/html-has-lang?application=axeAPI",
            "nodes": [
                {
                    "any": [
                        {
                            "id": "has-lang",
                            "data": null,
                            "relatedNodes": [],
                            "impact": "serious",
                            "message": "The <html> element has a lang attribute"
                        }
                    ],
                    "all": [],
                    "none": [],
                    "impact": null,
                    "html": "<html lang=\"en-US\" xml:lang=\"\" xmlns=\"http://www.w3.org/1999/xhtml\">",
                    "target": [
                        "html"
                    ]
                }
            ]
        },
        {
            "id": "html-lang-valid",
            "impact": null,
            "tags": [
                "cat.language",
                "wcag2a",
                "wcag311",
                "ACT"
            ],
            "description": "Ensures the lang attribute of the <html> element has a valid value",
            "help": "<html> element must have a valid value for the lang attribute",
            "helpUrl": "https://dequeuniversity.com/rules/axe/4.4/html-lang-valid?application=axeAPI",
            "nodes": [
                {
                    "any": [],
                    "all": [],
                    "none": [
                        {
                            "id": "valid-lang",
                            "data": null,
                            "relatedNodes": [],
                            "impact": "serious",
                            "message": "Value of lang attribute is included in the list of valid languages"
                        }
                    ],
                    "impact": null,
                    "html": "<html lang=\"en-US\" xml:lang=\"\" xmlns=\"http://www.w3.org/1999/xhtml\">",
                    "target": [
                        "html"
                    ]
                }
            ]
        },
        {
            "id": "identical-links-same-purpose",
            "impact": null,
            "tags": [
                "cat.semantics",
                "wcag2aaa",
                "wcag249"
            ],
            "description": "Ensure that links with the same accessible name serve a similar purpose",
            "help": "Links with the same name must have a similar purpose",
            "helpUrl": "https://dequeuniversity.com/rules/axe/4.4/identical-links-same-purpose?application=axeAPI",
            "nodes": [
                {
                    "any": [],
                    "all": [
                        {
                            "id": "identical-links-same-purpose",
                            "data": {
                                "name": "privacy policy",
                                "urlProps": {
                                    "protocol": "javascript:",
                                    "hostname": "",
                                    "port": "",
                                    "pathname": "/popSupportWin('http://3eco.com/privacy-policy')/",
                                    "search": {},
                                    "hash": "",
                                    "filename": ""
                                }
                            },
                            "relatedNodes": [],
                            "impact": "minor",
                            "message": "There are no other links with the same name, that go to a different URL"
                        }
                    ],
                    "none": [],
                    "impact": null,
                    "html": "<a href=\"javascript:popSupportWin('http://3eco.com/privacy-policy')\" class=\"MediumLink\" style=\"color: #0d4c68\">\n            <b>\n                Privacy Policy \n            </b>\n        </a>",
                    "target": [
                        "#div2 > .MediumLink:nth-child(1)"
                    ]
                }
            ]
        },
        {
            "id": "input-button-name",
            "impact": null,
            "tags": [
                "cat.name-role-value",
                "wcag2a",
                "wcag412",
                "section508",
                "section508.22.a"
            ],
            "description": "Ensures input buttons have discernible text",
            "help": "Input buttons must have discernible text",
            "helpUrl": "https://dequeuniversity.com/rules/axe/4.4/input-button-name?application=axeAPI",
            "nodes": [
                {
                    "any": [
                        {
                            "id": "non-empty-value",
                            "data": null,
                            "relatedNodes": [],
                            "impact": "critical",
                            "message": "Element has a non-empty value attribute"
                        }
                    ],
                    "all": [],
                    "none": [],
                    "impact": null,
                    "html": "<input type=\"submit\" name=\"ctl00$ctl00$ContentPlaceHolderWhole$ContentPlaceHolderContent$IdRegister\" value=\"Register Now\" onclick=\"Validation();WebForm_DoPostBackWithOptions(new WebForm_PostBackOptions(&quot;ctl00$ctl00$ContentPlaceHolderWhole$ContentPlaceHolderContent$IdRegister&quot;, &quot;&quot;, true, &quot;&quot;, &quot;&quot;, false, false))\" id=\"ctl00_ctl00_ContentPlaceHolderWhole_ContentPlaceHolderContent_IdRegister\" class=\"CommandButton\">",
                    "target": [
                        "#ctl00_ctl00_ContentPlaceHolderWhole_ContentPlaceHolderContent_IdRegister"
                    ]
                }
            ]
        },
        {
            "id": "label-title-only",
            "impact": null,
            "tags": [
                "cat.forms",
                "best-practice"
            ],
            "description": "Ensures that every form element has a visible label and is not solely labeled using hidden labels, or the title or aria-describedby attributes",
            "help": "Form elements should have a visible label",
            "helpUrl": "https://dequeuniversity.com/rules/axe/4.4/label-title-only?application=axeAPI",
            "nodes": [
                {
                    "any": [],
                    "all": [],
                    "none": [
                        {
                            "id": "title-only",
                            "data": null,
                            "relatedNodes": [],
                            "impact": "serious",
                            "message": "Form element does not solely use title attribute for its label"
                        }
                    ],
                    "impact": null,
                    "html": "<input name=\"ctl00$ctl00$ContentPlaceHolderWhole$ContentPlaceHolderContent$FirstName\" type=\"text\" id=\"ctl00_ctl00_ContentPlaceHolderWhole_ContentPlaceHolderContent_FirstName\" size=\"25\">",
                    "target": [
                        "#ctl00_ctl00_ContentPlaceHolderWhole_ContentPlaceHolderContent_FirstName"
                    ]
                }
            ]
        },
        {
            "id": "link-name",
            "impact": null,
            "tags": [
                "cat.name-role-value",
                "wcag2a",
                "wcag412",
                "wcag244",
                "section508",
                "section508.22.a",
                "ACT"
            ],
            "description": "Ensures links have discernible text",
            "help": "Links must have discernible text",
            "helpUrl": "https://dequeuniversity.com/rules/axe/4.4/link-name?application=axeAPI",
            "nodes": [
                {
                    "any": [
                        {
                            "id": "has-visible-text",
                            "data": null,
                            "relatedNodes": [],
                            "impact": "minor",
                            "message": "Element has text that is visible to screen readers"
                        }
                    ],
                    "all": [],
                    "none": [
                        {
                            "id": "focusable-no-name",
                            "data": null,
                            "relatedNodes": [],
                            "impact": "serious",
                            "message": "Element is not in tab order or has accessible text"
                        }
                    ],
                    "impact": null,
                    "html": "<a href=\"javascript:popSupportWin('http://3eco.com/privacy-policy')\" class=\"MediumLink\" style=\"color: #0d4c68\">\n            <b>\n                Privacy Policy \n            </b>\n        </a>",
                    "target": [
                        "#div2 > .MediumLink:nth-child(1)"
                    ]
                }
            ]
        },
        {
            "id": "nested-interactive",
            "impact": null,
            "tags": [
                "cat.keyboard",
                "wcag2a",
                "wcag412"
            ],
            "description": "Ensures interactive controls are not nested as they are not always announced by screen readers or can cause focus problems for assistive technologies",
            "help": "Interactive controls must not be nested",
            "helpUrl": "https://dequeuniversity.com/rules/axe/4.4/nested-interactive?application=axeAPI",
            "nodes": [
                {
                    "any": [
                        {
                            "id": "no-focusable-content",
                            "data": null,
                            "relatedNodes": [],
                            "impact": "serious",
                            "message": "Element does not have focusable descendants"
                        }
                    ],
                    "all": [],
                    "none": [],
                    "impact": null,
                    "html": "<hr>",
                    "target": [
                        "hr"
                    ]
                }
            ]
        },
        {
            "id": "region",
            "impact": "moderate",
            "tags": [
                "cat.keyboard",
                "best-practice"
            ],
            "description": "Ensures all page content is contained by landmarks",
            "help": "All page content should be contained by landmarks",
            "helpUrl": "https://dequeuniversity.com/rules/axe/4.4/region?application=axeAPI",
            "nodes": [
                {
                    "any": [
                        {
                            "id": "region",
                            "data": {
                                "isIframe": false
                            },
                            "relatedNodes": [],
                            "impact": "moderate",
                            "message": "All page content is contained by landmarks"
                        }
                    ],
                    "all": [],
                    "none": [],
                    "impact": null,
                    "html": "<br>",
                    "target": [
                        "body > br"
                    ]
                }
            ]
        },
        {
            "id": "tabindex",
            "impact": null,
            "tags": [
                "cat.keyboard",
                "best-practice"
            ],
            "description": "Ensures tabindex attribute values are not greater than 0",
            "help": "Elements should not have tabindex greater than zero",
            "helpUrl": "https://dequeuniversity.com/rules/axe/4.4/tabindex?application=axeAPI",
            "nodes": [
                {
                    "any": [
                        {
                            "id": "tabindex",
                            "data": null,
                            "relatedNodes": [],
                            "impact": "serious",
                            "message": "Element does not have a tabindex greater than 0"
                        }
                    ],
                    "all": [],
                    "none": [],
                    "impact": null,
                    "html": "<iframe src=\"https://newassets.hcaptcha.com/captcha/v1/11178f2/static/hcaptcha.html#frame=checkbox&amp;id=07w8soj8gzpd&amp;host=insightchemicals.3eiq.com&amp;sentry=undefined&amp;reportapi=https%3A%2F%2Faccounts.hcaptcha.com&amp;recaptchacompat=true&amp;custom=false&amp;tplinks=on&amp;pstissuer=https%3A%2F%2Fpst-issuer.hcaptcha.com&amp;sitekey=b12cd44a-ddd4-4170-9761-927030c07eb5&amp;theme=light&amp;origin=https%3A%2F%2Finsightchemicals.3eiq.com\" tabindex=\"0\" frameborder=\"0\" scrolling=\"no\" allow=\"private-state-token-issuance 'src'; private-state-token-redemption 'src'\" title=\"Widget containing checkbox for hCaptcha security challenge\" data-hcaptcha-widget-id=\"07w8soj8gzpd\" data-hcaptcha-response=\"\" style=\"pointer-events: auto; background-color: rgba(255, 255, 255, 0); width: 303px; height: 78px; overflow: hidden;\">",
                    "target": [
                        "iframe[data-hcaptcha-widget-id=\"07w8soj8gzpd\"]"
                    ]
                }
            ]
        },
        {
            "id": "table-duplicate-name",
            "impact": null,
            "tags": [
                "cat.tables",
                "best-practice"
            ],
            "description": "Ensure the <caption> element does not contain the same text as the summary attribute",
            "help": "tables should not have the same summary and caption",
            "helpUrl": "https://dequeuniversity.com/rules/axe/4.4/table-duplicate-name?application=axeAPI",
            "nodes": [
                {
                    "any": [],
                    "all": [],
                    "none": [
                        {
                            "id": "same-caption-summary",
                            "data": null,
                            "relatedNodes": [],
                            "impact": "minor",
                            "message": "Content of summary attribute and <caption> are not duplicated"
                        }
                    ],
                    "impact": null,
                    "html": "<table width=\"100%\" height=\"100%\" cellspacing=\"0\" cellpadding=\"0\" border=\"0\">",
                    "target": [
                        "table[height=\"100%\"][cellspacing=\"0\"][cellpadding=\"0\"]"
                    ]
                }
            ]
        },
        {
            "id": "td-headers-attr",
            "impact": null,
            "tags": [
                "cat.tables",
                "wcag2a",
                "wcag131",
                "section508",
                "section508.22.g"
            ],
            "description": "Ensure that each cell in a table that uses the headers attribute refers only to other cells in that table",
            "help": "Table cells that use the headers attribute must only refer to cells in the same table",
            "helpUrl": "https://dequeuniversity.com/rules/axe/4.4/td-headers-attr?application=axeAPI",
            "nodes": [
                {
                    "any": [],
                    "all": [
                        {
                            "id": "td-headers-attr",
                            "data": null,
                            "relatedNodes": [],
                            "impact": "serious",
                            "message": "The headers attribute is exclusively used to refer to other cells in the table"
                        }
                    ],
                    "none": [],
                    "impact": null,
                    "html": "<table width=\"100%\" height=\"100%\" cellspacing=\"0\" cellpadding=\"0\" border=\"0\">",
                    "target": [
                        "table[height=\"100%\"][cellspacing=\"0\"][cellpadding=\"0\"]"
                    ]
                }
            ]
        }
    ],
    "violations": [
        {
            "id": "avoid-inline-spacing",
            "impact": "serious",
            "tags": [
                "cat.structure",
                "wcag21aa",
                "wcag1412"
            ],
            "description": "Ensure that text spacing set through style attributes can be adjusted with custom stylesheets",
            "help": "Inline text spacing must be adjustable with custom stylesheets",
            "helpUrl": "https://dequeuniversity.com/rules/axe/4.4/avoid-inline-spacing?application=axeAPI",
            "nodes": [
                {
                    "any": [],
                    "all": [
                        {
                            "id": "avoid-inline-spacing",
                            "data": [
                                "line-height"
                            ],
                            "relatedNodes": [],
                            "impact": "serious",
                            "message": "Remove '!important' from inline style line-height, as overriding this is not supported by most browsers"
                        }
                    ],
                    "none": [],
                    "impact": "serious",
                    "html": "<span id=\"ctl00_ctl00_ContentPlaceHolderWhole_ContentPlaceHolderContent_Message\" style=\"font-weight:bold;color:red;font-weight:bolder;font-size:12px;line-height:14px!important\"></span>",
                    "target": [
                        "#ctl00_ctl00_ContentPlaceHolderWhole_ContentPlaceHolderContent_Message"
                    ],
                    "failureSummary": "Fix all of the following:\n  Remove '!important' from inline style line-height, as overriding this is not supported by most browsers"
                }
            ]
        },
        {
            "id": "label",
            "impact": "critical",
            "tags": [
                "cat.forms",
                "wcag2a",
                "wcag412",
                "wcag131",
                "section508",
                "section508.22.n",
                "ACT"
            ],
            "description": "Ensures every form element has a label",
            "help": "Form elements must have labels",
            "helpUrl": "https://dequeuniversity.com/rules/axe/4.4/label?application=axeAPI",
            "nodes": [
                {
                    "any": [
                        {
                            "id": "implicit-label",
                            "data": null,
                            "relatedNodes": [],
                            "impact": "critical",
                            "message": "Form element does not have an implicit (wrapped) <label>"
                        },
                        {
                            "id": "explicit-label",
                            "data": null,
                            "relatedNodes": [],
                            "impact": "critical",
                            "message": "Form element does not have an explicit <label>"
                        },
                        {
                            "id": "aria-label",
                            "data": null,
                            "relatedNodes": [],
                            "impact": "serious",
                            "message": "aria-label attribute does not exist or is empty"
                        },
                        {
                            "id": "aria-labelledby",
                            "data": null,
                            "relatedNodes": [],
                            "impact": "serious",
                            "message": "aria-labelledby attribute does not exist, references elements that do not exist or references elements that are empty"
                        },
                        {
                            "id": "non-empty-title",
                            "data": {
                                "messageKey": "noAttr"
                            },
                            "relatedNodes": [],
                            "impact": "serious",
                            "message": "Element has no title attribute"
                        },
                        {
                            "id": "non-empty-placeholder",
                            "data": {
                                "messageKey": "noAttr"
                            },
                            "relatedNodes": [],
                            "impact": "serious",
                            "message": "Element has no placeholder attribute"
                        },
                        {
                            "id": "presentational-role",
                            "data": null,
                            "relatedNodes": [],
                            "impact": "minor",
                            "message": "Element's default semantics were not overridden with role=\"none\" or role=\"presentation\""
                        }
                    ],
                    "all": [],
                    "none": [],
                    "impact": "critical",
                    "html": "<input name=\"ctl00$ctl00$ContentPlaceHolderWhole$ContentPlaceHolderContent$FirstName\" type=\"text\" id=\"ctl00_ctl00_ContentPlaceHolderWhole_ContentPlaceHolderContent_FirstName\" size=\"25\">",
                    "target": [
                        "#ctl00_ctl00_ContentPlaceHolderWhole_ContentPlaceHolderContent_FirstName"
                    ],
                    "failureSummary": "Fix any of the following:\n  Form element does not have an implicit (wrapped) <label>\n  Form element does not have an explicit <label>\n  aria-label attribute does not exist or is empty\n  aria-labelledby attribute does not exist, references elements that do not exist or references elements that are empty\n  Element has no title attribute\n  Element has no placeholder attribute\n  Element's default semantics were not overridden with role=\"none\" or role=\"presentation\""
                },
                {
                    "any": [
                        {
                            "id": "implicit-label",
                            "data": null,
                            "relatedNodes": [],
                            "impact": "critical",
                            "message": "Form element does not have an implicit (wrapped) <label>"
                        },
                        {
                            "id": "explicit-label",
                            "data": null,
                            "relatedNodes": [],
                            "impact": "critical",
                            "message": "Form element does not have an explicit <label>"
                        },
                        {
                            "id": "aria-label",
                            "data": null,
                            "relatedNodes": [],
                            "impact": "serious",
                            "message": "aria-label attribute does not exist or is empty"
                        },
                        {
                            "id": "aria-labelledby",
                            "data": null,
                            "relatedNodes": [],
                            "impact": "serious",
                            "message": "aria-labelledby attribute does not exist, references elements that do not exist or references elements that are empty"
                        },
                        {
                            "id": "non-empty-title",
                            "data": {
                                "messageKey": "noAttr"
                            },
                            "relatedNodes": [],
                            "impact": "serious",
                            "message": "Element has no title attribute"
                        },
                        {
                            "id": "non-empty-placeholder",
                            "data": {
                                "messageKey": "noAttr"
                            },
                            "relatedNodes": [],
                            "impact": "serious",
                            "message": "Element has no placeholder attribute"
                        },
                        {
                            "id": "presentational-role",
                            "data": null,
                            "relatedNodes": [],
                            "impact": "minor",
                            "message": "Element's default semantics were not overridden with role=\"none\" or role=\"presentation\""
                        }
                    ],
                    "all": [],
                    "none": [],
                    "impact": "critical",
                    "html": "<input name=\"ctl00$ctl00$ContentPlaceHolderWhole$ContentPlaceHolderContent$LastName\" type=\"text\" id=\"ctl00_ctl00_ContentPlaceHolderWhole_ContentPlaceHolderContent_LastName\" size=\"25\">",
                    "target": [
                        "#ctl00_ctl00_ContentPlaceHolderWhole_ContentPlaceHolderContent_LastName"
                    ],
                    "failureSummary": "Fix any of the following:\n  Form element does not have an implicit (wrapped) <label>\n  Form element does not have an explicit <label>\n  aria-label attribute does not exist or is empty\n  aria-labelledby attribute does not exist, references elements that do not exist or references elements that are empty\n  Element has no title attribute\n  Element has no placeholder attribute\n  Element's default semantics were not overridden with role=\"none\" or role=\"presentation\""
                },
                {
                    "any": [
                        {
                            "id": "implicit-label",
                            "data": null,
                            "relatedNodes": [],
                            "impact": "critical",
                            "message": "Form element does not have an implicit (wrapped) <label>"
                        },
                        {
                            "id": "explicit-label",
                            "data": null,
                            "relatedNodes": [],
                            "impact": "critical",
                            "message": "Form element does not have an explicit <label>"
                        },
                        {
                            "id": "aria-label",
                            "data": null,
                            "relatedNodes": [],
                            "impact": "serious",
                            "message": "aria-label attribute does not exist or is empty"
                        },
                        {
                            "id": "aria-labelledby",
                            "data": null,
                            "relatedNodes": [],
                            "impact": "serious",
                            "message": "aria-labelledby attribute does not exist, references elements that do not exist or references elements that are empty"
                        },
                        {
                            "id": "non-empty-title",
                            "data": {
                                "messageKey": "noAttr"
                            },
                            "relatedNodes": [],
                            "impact": "serious",
                            "message": "Element has no title attribute"
                        },
                        {
                            "id": "non-empty-placeholder",
                            "data": {
                                "messageKey": "noAttr"
                            },
                            "relatedNodes": [],
                            "impact": "serious",
                            "message": "Element has no placeholder attribute"
                        },
                        {
                            "id": "presentational-role",
                            "data": null,
                            "relatedNodes": [],
                            "impact": "minor",
                            "message": "Element's default semantics were not overridden with role=\"none\" or role=\"presentation\""
                        }
                    ],
                    "all": [],
                    "none": [],
                    "impact": "critical",
                    "html": "<input name=\"ctl00$ctl00$ContentPlaceHolderWhole$ContentPlaceHolderContent$Username\" type=\"text\" id=\"ctl00_ctl00_ContentPlaceHolderWhole_ContentPlaceHolderContent_Username\" size=\"25\">",
                    "target": [
                        "#ctl00_ctl00_ContentPlaceHolderWhole_ContentPlaceHolderContent_Username"
                    ],
                    "failureSummary": "Fix any of the following:\n  Form element does not have an implicit (wrapped) <label>\n  Form element does not have an explicit <label>\n  aria-label attribute does not exist or is empty\n  aria-labelledby attribute does not exist, references elements that do not exist or references elements that are empty\n  Element has no title attribute\n  Element has no placeholder attribute\n  Element's default semantics were not overridden with role=\"none\" or role=\"presentation\""
                },
                {
                    "any": [
                        {
                            "id": "implicit-label",
                            "data": null,
                            "relatedNodes": [],
                            "impact": "critical",
                            "message": "Form element does not have an implicit (wrapped) <label>"
                        },
                        {
                            "id": "explicit-label",
                            "data": null,
                            "relatedNodes": [],
                            "impact": "critical",
                            "message": "Form element does not have an explicit <label>"
                        },
                        {
                            "id": "aria-label",
                            "data": null,
                            "relatedNodes": [],
                            "impact": "serious",
                            "message": "aria-label attribute does not exist or is empty"
                        },
                        {
                            "id": "aria-labelledby",
                            "data": null,
                            "relatedNodes": [],
                            "impact": "serious",
                            "message": "aria-labelledby attribute does not exist, references elements that do not exist or references elements that are empty"
                        },
                        {
                            "id": "non-empty-title",
                            "data": {
                                "messageKey": "noAttr"
                            },
                            "relatedNodes": [],
                            "impact": "serious",
                            "message": "Element has no title attribute"
                        },
                        {
                            "id": "non-empty-placeholder",
                            "data": {
                                "messageKey": "noAttr"
                            },
                            "relatedNodes": [],
                            "impact": "serious",
                            "message": "Element has no placeholder attribute"
                        },
                        {
                            "id": "presentational-role",
                            "data": null,
                            "relatedNodes": [],
                            "impact": "minor",
                            "message": "Element's default semantics were not overridden with role=\"none\" or role=\"presentation\""
                        }
                    ],
                    "all": [],
                    "none": [],
                    "impact": "critical",
                    "html": "<input name=\"ctl00$ctl00$ContentPlaceHolderWhole$ContentPlaceHolderContent$Email\" type=\"text\" id=\"ctl00_ctl00_ContentPlaceHolderWhole_ContentPlaceHolderContent_Email\" size=\"25\">",
                    "target": [
                        "#ctl00_ctl00_ContentPlaceHolderWhole_ContentPlaceHolderContent_Email"
                    ],
                    "failureSummary": "Fix any of the following:\n  Form element does not have an implicit (wrapped) <label>\n  Form element does not have an explicit <label>\n  aria-label attribute does not exist or is empty\n  aria-labelledby attribute does not exist, references elements that do not exist or references elements that are empty\n  Element has no title attribute\n  Element has no placeholder attribute\n  Element's default semantics were not overridden with role=\"none\" or role=\"presentation\""
                },
                {
                    "any": [
                        {
                            "id": "implicit-label",
                            "data": null,
                            "relatedNodes": [],
                            "impact": "critical",
                            "message": "Form element does not have an implicit (wrapped) <label>"
                        },
                        {
                            "id": "explicit-label",
                            "data": null,
                            "relatedNodes": [],
                            "impact": "critical",
                            "message": "Form element does not have an explicit <label>"
                        },
                        {
                            "id": "aria-label",
                            "data": null,
                            "relatedNodes": [],
                            "impact": "serious",
                            "message": "aria-label attribute does not exist or is empty"
                        },
                        {
                            "id": "aria-labelledby",
                            "data": null,
                            "relatedNodes": [],
                            "impact": "serious",
                            "message": "aria-labelledby attribute does not exist, references elements that do not exist or references elements that are empty"
                        },
                        {
                            "id": "non-empty-title",
                            "data": {
                                "messageKey": "noAttr"
                            },
                            "relatedNodes": [],
                            "impact": "serious",
                            "message": "Element has no title attribute"
                        },
                        {
                            "id": "non-empty-placeholder",
                            "data": {
                                "messageKey": "noAttr"
                            },
                            "relatedNodes": [],
                            "impact": "serious",
                            "message": "Element has no placeholder attribute"
                        },
                        {
                            "id": "presentational-role",
                            "data": null,
                            "relatedNodes": [],
                            "impact": "minor",
                            "message": "Element's default semantics were not overridden with role=\"none\" or role=\"presentation\""
                        }
                    ],
                    "all": [],
                    "none": [],
                    "impact": "critical",
                    "html": "<input name=\"ctl00$ctl00$ContentPlaceHolderWhole$ContentPlaceHolderContent$Password\" type=\"password\" id=\"ctl00_ctl00_ContentPlaceHolderWhole_ContentPlaceHolderContent_Password\" size=\"25\">",
                    "target": [
                        "#ctl00_ctl00_ContentPlaceHolderWhole_ContentPlaceHolderContent_Password"
                    ],
                    "failureSummary": "Fix any of the following:\n  Form element does not have an implicit (wrapped) <label>\n  Form element does not have an explicit <label>\n  aria-label attribute does not exist or is empty\n  aria-labelledby attribute does not exist, references elements that do not exist or references elements that are empty\n  Element has no title attribute\n  Element has no placeholder attribute\n  Element's default semantics were not overridden with role=\"none\" or role=\"presentation\""
                },
                {
                    "any": [
                        {
                            "id": "implicit-label",
                            "data": null,
                            "relatedNodes": [],
                            "impact": "critical",
                            "message": "Form element does not have an implicit (wrapped) <label>"
                        },
                        {
                            "id": "explicit-label",
                            "data": null,
                            "relatedNodes": [],
                            "impact": "critical",
                            "message": "Form element does not have an explicit <label>"
                        },
                        {
                            "id": "aria-label",
                            "data": null,
                            "relatedNodes": [],
                            "impact": "serious",
                            "message": "aria-label attribute does not exist or is empty"
                        },
                        {
                            "id": "aria-labelledby",
                            "data": null,
                            "relatedNodes": [],
                            "impact": "serious",
                            "message": "aria-labelledby attribute does not exist, references elements that do not exist or references elements that are empty"
                        },
                        {
                            "id": "non-empty-title",
                            "data": {
                                "messageKey": "noAttr"
                            },
                            "relatedNodes": [],
                            "impact": "serious",
                            "message": "Element has no title attribute"
                        },
                        {
                            "id": "non-empty-placeholder",
                            "data": {
                                "messageKey": "noAttr"
                            },
                            "relatedNodes": [],
                            "impact": "serious",
                            "message": "Element has no placeholder attribute"
                        },
                        {
                            "id": "presentational-role",
                            "data": null,
                            "relatedNodes": [],
                            "impact": "minor",
                            "message": "Element's default semantics were not overridden with role=\"none\" or role=\"presentation\""
                        }
                    ],
                    "all": [],
                    "none": [],
                    "impact": "critical",
                    "html": "<input name=\"ctl00$ctl00$ContentPlaceHolderWhole$ContentPlaceHolderContent$ConfirmPassword\" type=\"password\" id=\"ctl00_ctl00_ContentPlaceHolderWhole_ContentPlaceHolderContent_ConfirmPassword\" size=\"25\">",
                    "target": [
                        "#ctl00_ctl00_ContentPlaceHolderWhole_ContentPlaceHolderContent_ConfirmPassword"
                    ],
                    "failureSummary": "Fix any of the following:\n  Form element does not have an implicit (wrapped) <label>\n  Form element does not have an explicit <label>\n  aria-label attribute does not exist or is empty\n  aria-labelledby attribute does not exist, references elements that do not exist or references elements that are empty\n  Element has no title attribute\n  Element has no placeholder attribute\n  Element's default semantics were not overridden with role=\"none\" or role=\"presentation\""
                },
                {
                    "any": [
                        {
                            "id": "implicit-label",
                            "data": null,
                            "relatedNodes": [],
                            "impact": "critical",
                            "message": "Form element does not have an implicit (wrapped) <label>"
                        },
                        {
                            "id": "explicit-label",
                            "data": null,
                            "relatedNodes": [],
                            "impact": "critical",
                            "message": "Form element does not have an explicit <label>"
                        },
                        {
                            "id": "aria-label",
                            "data": null,
                            "relatedNodes": [],
                            "impact": "serious",
                            "message": "aria-label attribute does not exist or is empty"
                        },
                        {
                            "id": "aria-labelledby",
                            "data": null,
                            "relatedNodes": [],
                            "impact": "serious",
                            "message": "aria-labelledby attribute does not exist, references elements that do not exist or references elements that are empty"
                        },
                        {
                            "id": "non-empty-title",
                            "data": {
                                "messageKey": "noAttr"
                            },
                            "relatedNodes": [],
                            "impact": "serious",
                            "message": "Element has no title attribute"
                        },
                        {
                            "id": "non-empty-placeholder",
                            "data": {
                                "messageKey": "noAttr"
                            },
                            "relatedNodes": [],
                            "impact": "serious",
                            "message": "Element has no placeholder attribute"
                        },
                        {
                            "id": "presentational-role",
                            "data": null,
                            "relatedNodes": [],
                            "impact": "minor",
                            "message": "Element's default semantics were not overridden with role=\"none\" or role=\"presentation\""
                        }
                    ],
                    "all": [],
                    "none": [],
                    "impact": "critical",
                    "html": "<input name=\"ctl00$ctl00$ContentPlaceHolderWhole$ContentPlaceHolderContent$N00000006fcw3\" type=\"checkbox\" id=\"ctl00_ctl00_ContentPlaceHolderWhole_ContentPlaceHolderContent_N00000006fcw3\" value=\"Yes\" checked=\"checked\">",
                    "target": [
                        "#ctl00_ctl00_ContentPlaceHolderWhole_ContentPlaceHolderContent_N00000006fcw3"
                    ],
                    "failureSummary": "Fix any of the following:\n  Form element does not have an implicit (wrapped) <label>\n  Form element does not have an explicit <label>\n  aria-label attribute does not exist or is empty\n  aria-labelledby attribute does not exist, references elements that do not exist or references elements that are empty\n  Element has no title attribute\n  Element has no placeholder attribute\n  Element's default semantics were not overridden with role=\"none\" or role=\"presentation\""
                },
                {
                    "any": [
                        {
                            "id": "implicit-label",
                            "data": null,
                            "relatedNodes": [],
                            "impact": "critical",
                            "message": "Form element does not have an implicit (wrapped) <label>"
                        },
                        {
                            "id": "explicit-label",
                            "data": null,
                            "relatedNodes": [],
                            "impact": "critical",
                            "message": "Form element does not have an explicit <label>"
                        },
                        {
                            "id": "aria-label",
                            "data": null,
                            "relatedNodes": [],
                            "impact": "serious",
                            "message": "aria-label attribute does not exist or is empty"
                        },
                        {
                            "id": "aria-labelledby",
                            "data": null,
                            "relatedNodes": [],
                            "impact": "serious",
                            "message": "aria-labelledby attribute does not exist, references elements that do not exist or references elements that are empty"
                        },
                        {
                            "id": "non-empty-title",
                            "data": {
                                "messageKey": "noAttr"
                            },
                            "relatedNodes": [],
                            "impact": "serious",
                            "message": "Element has no title attribute"
                        },
                        {
                            "id": "non-empty-placeholder",
                            "data": {
                                "messageKey": "noAttr"
                            },
                            "relatedNodes": [],
                            "impact": "serious",
                            "message": "Element has no placeholder attribute"
                        },
                        {
                            "id": "presentational-role",
                            "data": null,
                            "relatedNodes": [],
                            "impact": "minor",
                            "message": "Element's default semantics were not overridden with role=\"none\" or role=\"presentation\""
                        }
                    ],
                    "all": [],
                    "none": [],
                    "impact": "critical",
                    "html": "<input name=\"ctl00$ctl00$ContentPlaceHolderWhole$ContentPlaceHolderContent$N00000006fd1z\" type=\"checkbox\" id=\"ctl00_ctl00_ContentPlaceHolderWhole_ContentPlaceHolderContent_N00000006fd1z\" value=\"Yes\" checked=\"checked\">",
                    "target": [
                        "#ctl00_ctl00_ContentPlaceHolderWhole_ContentPlaceHolderContent_N00000006fd1z"
                    ],
                    "failureSummary": "Fix any of the following:\n  Form element does not have an implicit (wrapped) <label>\n  Form element does not have an explicit <label>\n  aria-label attribute does not exist or is empty\n  aria-labelledby attribute does not exist, references elements that do not exist or references elements that are empty\n  Element has no title attribute\n  Element has no placeholder attribute\n  Element's default semantics were not overridden with role=\"none\" or role=\"presentation\""
                },
                {
                    "any": [
                        {
                            "id": "implicit-label",
                            "data": null,
                            "relatedNodes": [],
                            "impact": "critical",
                            "message": "Form element does not have an implicit (wrapped) <label>"
                        },
                        {
                            "id": "explicit-label",
                            "data": null,
                            "relatedNodes": [],
                            "impact": "critical",
                            "message": "Form element does not have an explicit <label>"
                        },
                        {
                            "id": "aria-label",
                            "data": null,
                            "relatedNodes": [],
                            "impact": "serious",
                            "message": "aria-label attribute does not exist or is empty"
                        },
                        {
                            "id": "aria-labelledby",
                            "data": null,
                            "relatedNodes": [],
                            "impact": "serious",
                            "message": "aria-labelledby attribute does not exist, references elements that do not exist or references elements that are empty"
                        },
                        {
                            "id": "non-empty-title",
                            "data": {
                                "messageKey": "noAttr"
                            },
                            "relatedNodes": [],
                            "impact": "serious",
                            "message": "Element has no title attribute"
                        },
                        {
                            "id": "non-empty-placeholder",
                            "data": {
                                "messageKey": "noAttr"
                            },
                            "relatedNodes": [],
                            "impact": "serious",
                            "message": "Element has no placeholder attribute"
                        },
                        {
                            "id": "presentational-role",
                            "data": null,
                            "relatedNodes": [],
                            "impact": "minor",
                            "message": "Element's default semantics were not overridden with role=\"none\" or role=\"presentation\""
                        }
                    ],
                    "all": [],
                    "none": [],
                    "impact": "critical",
                    "html": "<input value=\"HTML\" name=\"ctl00$ctl00$ContentPlaceHolderWhole$ContentPlaceHolderContent$00N00000006fcxI\" type=\"Radio\" id=\"ctl00_ctl00_ContentPlaceHolderWhole_ContentPlaceHolderContent_N00000006fcxI1\" checked=\"checked\">",
                    "target": [
                        "#ctl00_ctl00_ContentPlaceHolderWhole_ContentPlaceHolderContent_N00000006fcxI1"
                    ],
                    "failureSummary": "Fix any of the following:\n  Form element does not have an implicit (wrapped) <label>\n  Form element does not have an explicit <label>\n  aria-label attribute does not exist or is empty\n  aria-labelledby attribute does not exist, references elements that do not exist or references elements that are empty\n  Element has no title attribute\n  Element has no placeholder attribute\n  Element's default semantics were not overridden with role=\"none\" or role=\"presentation\""
                },
                {
                    "any": [
                        {
                            "id": "implicit-label",
                            "data": null,
                            "relatedNodes": [],
                            "impact": "critical",
                            "message": "Form element does not have an implicit (wrapped) <label>"
                        },
                        {
                            "id": "explicit-label",
                            "data": null,
                            "relatedNodes": [],
                            "impact": "critical",
                            "message": "Form element does not have an explicit <label>"
                        },
                        {
                            "id": "aria-label",
                            "data": null,
                            "relatedNodes": [],
                            "impact": "serious",
                            "message": "aria-label attribute does not exist or is empty"
                        },
                        {
                            "id": "aria-labelledby",
                            "data": null,
                            "relatedNodes": [],
                            "impact": "serious",
                            "message": "aria-labelledby attribute does not exist, references elements that do not exist or references elements that are empty"
                        },
                        {
                            "id": "non-empty-title",
                            "data": {
                                "messageKey": "noAttr"
                            },
                            "relatedNodes": [],
                            "impact": "serious",
                            "message": "Element has no title attribute"
                        },
                        {
                            "id": "non-empty-placeholder",
                            "data": {
                                "messageKey": "noAttr"
                            },
                            "relatedNodes": [],
                            "impact": "serious",
                            "message": "Element has no placeholder attribute"
                        },
                        {
                            "id": "presentational-role",
                            "data": null,
                            "relatedNodes": [],
                            "impact": "minor",
                            "message": "Element's default semantics were not overridden with role=\"none\" or role=\"presentation\""
                        }
                    ],
                    "all": [],
                    "none": [],
                    "impact": "critical",
                    "html": "<input value=\"Text\" name=\"ctl00$ctl00$ContentPlaceHolderWhole$ContentPlaceHolderContent$00N00000006fcxI\" type=\"Radio\" id=\"ctl00_ctl00_ContentPlaceHolderWhole_ContentPlaceHolderContent_N00000006fcxI2\">",
                    "target": [
                        "#ctl00_ctl00_ContentPlaceHolderWhole_ContentPlaceHolderContent_N00000006fcxI2"
                    ],
                    "failureSummary": "Fix any of the following:\n  Form element does not have an implicit (wrapped) <label>\n  Form element does not have an explicit <label>\n  aria-label attribute does not exist or is empty\n  aria-labelledby attribute does not exist, references elements that do not exist or references elements that are empty\n  Element has no title attribute\n  Element has no placeholder attribute\n  Element's default semantics were not overridden with role=\"none\" or role=\"presentation\""
                }
            ]
        },
        {
            "id": "landmark-one-main",
            "impact": "moderate",
            "tags": [
                "cat.semantics",
                "best-practice"
            ],
            "description": "Ensures the document has a main landmark",
            "help": "Document should have one main landmark",
            "helpUrl": "https://dequeuniversity.com/rules/axe/4.4/landmark-one-main?application=axeAPI",
            "nodes": [
                {
                    "any": [],
                    "all": [
                        {
                            "id": "page-has-main",
                            "data": null,
                            "relatedNodes": [],
                            "impact": "moderate",
                            "message": "Document does not have a main landmark"
                        }
                    ],
                    "none": [],
                    "impact": "moderate",
                    "html": "<html lang=\"en-US\" xml:lang=\"\" xmlns=\"http://www.w3.org/1999/xhtml\">",
                    "target": [
                        "html"
                    ],
                    "failureSummary": "Fix all of the following:\n  Document does not have a main landmark"
                }
            ]
        },
        {
            "id": "page-has-heading-one",
            "impact": "moderate",
            "tags": [
                "cat.semantics",
                "best-practice"
            ],
            "description": "Ensure that the page, or at least one of its frames contains a level-one heading",
            "help": "Page should contain a level-one heading",
            "helpUrl": "https://dequeuniversity.com/rules/axe/4.4/page-has-heading-one?application=axeAPI",
            "nodes": [
                {
                    "any": [],
                    "all": [
                        {
                            "id": "page-has-heading-one",
                            "data": null,
                            "relatedNodes": [],
                            "impact": "moderate",
                            "message": "Page must have a level-one heading"
                        }
                    ],
                    "none": [],
                    "impact": "moderate",
                    "html": "<html lang=\"en-US\" xml:lang=\"\" xmlns=\"http://www.w3.org/1999/xhtml\">",
                    "target": [
                        "html"
                    ],
                    "failureSummary": "Fix all of the following:\n  Page must have a level-one heading"
                }
            ]
        },
        {
            "id": "region",
            "impact": "moderate",
            "tags": [
                "cat.keyboard",
                "best-practice"
            ],
            "description": "Ensures all page content is contained by landmarks",
            "help": "All page content should be contained by landmarks",
            "helpUrl": "https://dequeuniversity.com/rules/axe/4.4/region?application=axeAPI",
            "nodes": [
                {
                    "any": [
                        {
                            "id": "region",
                            "data": {
                                "isIframe": false
                            },
                            "relatedNodes": [],
                            "impact": "moderate",
                            "message": "Some page content is not contained by landmarks"
                        }
                    ],
                    "all": [],
                    "none": [],
                    "impact": "moderate",
                    "html": "<tr>\n            <td>\n                <span class=\"Head\">\n                    Create a New Account\n                </span>\n                <hr>\n            </td>\n        </tr>",
                    "target": [
                        "table[cellpadding=\"2\"] > tbody > tr:nth-child(1)"
                    ],
                    "failureSummary": "Fix any of the following:\n  Some page content is not contained by landmarks"
                },
                {
                    "any": [
                        {
                            "id": "region",
                            "data": {
                                "isIframe": false
                            },
                            "relatedNodes": [],
                            "impact": "moderate",
                            "message": "Some page content is not contained by landmarks"
                        }
                    ],
                    "all": [],
                    "none": [],
                    "impact": "moderate",
                    "html": "<div id=\"ctl00_ctl00_ContentPlaceHolderWhole_ContentPlaceHolderContent_LogonPanel\">",
                    "target": [
                        "#ctl00_ctl00_ContentPlaceHolderWhole_ContentPlaceHolderContent_LogonPanel"
                    ],
                    "failureSummary": "Fix any of the following:\n  Some page content is not contained by landmarks"
                },
                {
                    "any": [
                        {
                            "id": "region",
                            "data": {
                                "isIframe": false
                            },
                            "relatedNodes": [],
                            "impact": "moderate",
                            "message": "Some page content is not contained by landmarks"
                        }
                    ],
                    "all": [],
                    "none": [],
                    "impact": "moderate",
                    "html": "<div id=\"div2\" style=\"margin-top: 7%; margin-left: 30%\">",
                    "target": [
                        "#div2"
                    ],
                    "failureSummary": "Fix any of the following:\n  Some page content is not contained by landmarks"
                }
            ]
        },
        {
            "id": "select-name",
            "impact": "critical",
            "tags": [
                "cat.forms",
                "wcag2a",
                "wcag412",
                "wcag131",
                "section508",
                "section508.22.n",
                "ACT"
            ],
            "description": "Ensures select element has an accessible name",
            "help": "Select element must have an accessible name",
            "helpUrl": "https://dequeuniversity.com/rules/axe/4.4/select-name?application=axeAPI",
            "nodes": [
                {
                    "any": [
                        {
                            "id": "implicit-label",
                            "data": null,
                            "relatedNodes": [],
                            "impact": "critical",
                            "message": "Form element does not have an implicit (wrapped) <label>"
                        },
                        {
                            "id": "explicit-label",
                            "data": null,
                            "relatedNodes": [],
                            "impact": "critical",
                            "message": "Form element does not have an explicit <label>"
                        },
                        {
                            "id": "aria-label",
                            "data": null,
                            "relatedNodes": [],
                            "impact": "serious",
                            "message": "aria-label attribute does not exist or is empty"
                        },
                        {
                            "id": "aria-labelledby",
                            "data": null,
                            "relatedNodes": [],
                            "impact": "serious",
                            "message": "aria-labelledby attribute does not exist, references elements that do not exist or references elements that are empty"
                        },
                        {
                            "id": "non-empty-title",
                            "data": {
                                "messageKey": "noAttr"
                            },
                            "relatedNodes": [],
                            "impact": "serious",
                            "message": "Element has no title attribute"
                        },
                        {
                            "id": "presentational-role",
                            "data": null,
                            "relatedNodes": [],
                            "impact": "minor",
                            "message": "Element's default semantics were not overridden with role=\"none\" or role=\"presentation\""
                        }
                    ],
                    "all": [],
                    "none": [],
                    "impact": "critical",
                    "html": "<select name=\"ctl00$ctl00$ContentPlaceHolderWhole$ContentPlaceHolderContent$ddlCountry\" id=\"ctl00_ctl00_ContentPlaceHolderWhole_ContentPlaceHolderContent_ddlCountry\">",
                    "target": [
                        "#ctl00_ctl00_ContentPlaceHolderWhole_ContentPlaceHolderContent_ddlCountry"
                    ],
                    "failureSummary": "Fix any of the following:\n  Form element does not have an implicit (wrapped) <label>\n  Form element does not have an explicit <label>\n  aria-label attribute does not exist or is empty\n  aria-labelledby attribute does not exist, references elements that do not exist or references elements that are empty\n  Element has no title attribute\n  Element's default semantics were not overridden with role=\"none\" or role=\"presentation\""
                }
            ]
        }
    ]
}